bp_feature_importance/__init__.py
bp_feature_importance/feature_importance.py
bp_feature_importance-0.0.3.dist-info/LICENSE
bp_feature_importance-0.0.3.dist-info/METADATA
bp_feature_importance-0.0.3.dist-info/WHEEL
bp_feature_importance-0.0.3.dist-info/top_level.txt
bp_feature_importance-0.0.3.dist-info/RECORD
